LICENSE.txt
MANIFEST.in
setup.py
pyAppControl/__init__.py
pyAppControl.egg-info/PKG-INFO
pyAppControl.egg-info/SOURCES.txt
pyAppControl.egg-info/dependency_links.txt
pyAppControl.egg-info/requires.txt
pyAppControl.egg-info/top_level.txt
pyAppControl/Qianniu/__init__.py
pyAppControl/Qianniu/__pycache__/__init__.cpython-38.pyc
pyAppControl/Win64ControlQianniu/EntityFramework.SqlServer.dll
pyAppControl/Win64ControlQianniu/EntityFramework.SqlServer.xml
pyAppControl/Win64ControlQianniu/EntityFramework.dll
pyAppControl/Win64ControlQianniu/EntityFramework.xml
pyAppControl/Win64ControlQianniu/System.Data.SQLite.EF6.dll
pyAppControl/Win64ControlQianniu/System.Data.SQLite.Linq.dll
pyAppControl/Win64ControlQianniu/System.Data.SQLite.dll
pyAppControl/Win64ControlQianniu/System.Data.SQLite.xml
pyAppControl/Win64ControlQianniu/Win64ControlQianniu.dll
pyAppControl/Win64ControlQianniu/Win64ControlQianniu.dll.config
pyAppControl/Win64ControlQianniu/Win64ControlQianniu.pdb
pyAppControl/Win64ControlQianniu/Win64MKC.dll
pyAppControl/Win64ControlQianniu/x64/SQLite.Interop.dll
pyAppControl/Win64ControlQianniu/x86/SQLite.Interop.dll