Metadata-Version: 2.1
Name: pyAppControl
Version: 1.0.5
Summary: 基于 C# 开发的客户端控制程序。用于给一些存在大量重复性的软件操作场景提供技术支持。后续会逐渐提供相应的 App 控制解决方案。仅支持 x64 位 Windows 系统
Home-page: https://gitee.com/Yogurt_cry/pyAppControl
Author: Yogurt_cry
Author-email: ben.2001@foxmail.com
License: UNKNOWN
Platform: UNKNOWN
Classifier: Programming Language :: Python :: 3 :: Only
Classifier: License :: OSI Approved :: MIT License
Classifier: Operating System :: OS Independent
Requires-Python: >=3
License-File: LICENSE.txt
